{
  "basics": {
    "name": "Tamela Brinson",
    "label": "Computer Science Student",
    "picture": "https://avatars.githubusercontent.com/u/190249950?s=400&u=f64ac15936eecd63ee1188469c692195a5b57028&v=4",
    "email": "tamelab@hawaii.edu",
    "phone": "850-464-4311",
    "website": "https://tamelab.github.io",
    "summary": "Computer Science student at the University of Hawaiʻi at Mānoa with hands-on experience in software development, AI applications, web development, and cybersecurity research. Skilled in Java, Python, and C/C++, with strengths in problem-solving, teamwork, and project management.",
    "location": {
      "address": "",
      "postalCode": "96797",
      "city": "Waipahu",
      "countryCode": "US",
      "region": "HI"
    },
    "profiles": [
      { "network": "github", "username": "Tamelab", "url": "https://github.com/Tamelab" },
      { "network": "linkedin", "username": "tamelabrinson", "url": "https://linkedin.com/in/tamelabrinson" }
    ]
  },

  "interests": [
    { "name": "Cybersecurity" },
    { "name": "Artificial Intelligence" },
    { "name": "Software Development" },
    { "name": "Game Development" },
    { "name": "UX Design" }
  ],

  "skills": [
    {
      "name": "Programming",
      "keywords": ["Java", "Python", "C/C++"]
    },
    {
      "name": "Web Development",
      "keywords": ["HTML", "WordPress", "ADA-compliant Design", "Content Management"]
    },
    {
      "name": "Tools & Software",
      "keywords": ["Unity", "Photoshop", "Illustrator"]
    },
    {
      "name": "Systems",
      "keywords": ["Windows 10/11", "macOS"]
    }
  ],

  "education": [
    {
      "institution": "University of Hawaiʻi at Mānoa",
      "area": "Computer Science",
      "studyType": "Bachelor of Science",
      "startDate": "2023-08-01",
      "endDate": "Present",
      "courses": [
        "Data Security and Cryptography",
        "Software Engineering",
        "Artificial Intelligence and Machine Learning"
      ]
    },
    {
      "institution": "San Diego Community College Miramar",
      "area": "Computer Science",
      "studyType": "Associate of Science",
      "startDate": "2021-08-01",
      "endDate": "2023-05-01",
      "courses": []
    }
  ],

  "work": [
    {
      "company": "U.S. Navy",
      "position": "Elevator Technician / Ordnance Handler & Builder",
      "website": "",
      "startDate": "2013-01-01",
      "endDate": "2018-01-01",
      "summary": "Maintained mission-critical technical systems and supported operational readiness.",
      "highlights": [
        "Troubleshot complex technical systems",
        "Maintained high-reliability operational equipment",
        "Trained team members in technical procedures",
        "Developed leadership and advanced problem-solving skills"
      ]
    }
  ],

  "volunteer": [
    {
      "organization": "Habitat for Humanity",
      "website": "",
      "position": "Volunteer",
      "startDate": "2016-01-01",
      "endDate": "2016-12-31",
      "summary": "Assisted in collaborative community rehabilitation projects.",
      "highlights": [
        "Demonstrated initiative and organization",
        "Worked effectively in team-based environments",
        "Maintained strong attention to detail"
      ]
    }
  ],

  "awards": [],

  "references": [
    {
      "name": "Available upon request"
    }
  ]
}
